{
  "_instructions": "Client intake for Camenzuli Dental Excellence - extracted from master document",
  "_scaffold_command": "npm run scaffold",

  "client_slug": "camenzuli-dental",
  "template": "t2",

  "practice": {
    "name": "Camenzuli Dental Excellence",
    "tagline_override": null,
    "phone": "(504) 899-3080",
    "phone_link": "tel:+15048993080",
    "address": {
      "street": "5100 Tchoupitoulas Street, Third Floor",
      "city": "New Orleans",
      "state": "LA",
      "zip": "70115"
    },
    "hours": {
      "monday": "8:00 AM - 5:00 PM",
      "tuesday": "8:00 AM - 5:00 PM",
      "wednesday": "8:00 AM - 5:00 PM",
      "thursday": "8:00 AM - 5:00 PM",
      "friday": "Closed",
      "saturday": "Closed",
      "sunday": "Closed"
    }
  },

  "doctor": {
    "name": "Dr. Camenzuli, DDS",
    "title": "FAGD, ICOI, FACD - General & Sedation Dentist",
    "years_experience": 25,
    "credentials": [
      "Fellow, Academy of General Dentistry (FAGD)",
      "Fellow, International College of Oral Implantologists (ICOI)",
      "Fellow, American College of Dentists (FACD)",
      "Near-Mastership AGD (58 CE hours toward MAGD)",
      "IV Sedation Licensed",
      "ZBLC Immediate Implant Protocol Certified",
      "14 Years In-House Orthodontics"
    ],
    "bio_short": "Dr. Camenzuli has spent 25 years building the clinical capability to help patients who would otherwise avoid care entirely. His mother lost all her teeth by age 16 due to dental fear - that experience drove him to pursue three fellowships, IV sedation licensure, and advanced implant protocols. He treats the full scope of dental care in-house, without the referrals and fragmented experience that most general practices require."
  },

  "booking_link": "https://camenzulidentalexcellence.com/book",

  "brand": {
    "accent_color": "#0ea5e9",
    "logo_path": "/images/logo-camenzuli.svg"
  },

  "membership": {
    "individual_price": 299,
    "couple_price": 549,
    "family_price": 899,
    "no_insurance_savings_plan_price": 249
  },

  "stats": {
    "google_rating": 4.9,
    "review_count": 50,
    "patients_served": 5000,
    "satisfaction_rate": 98
  },

  "vercel": {
    "project_name": "camenzuli-dental",
    "domain": "camenzulidentalexcellence.com"
  }
}
